rootlearn/__init__.py
rootlearn/models/__init__.py
rootlearn/models/decision_tree.py
rootlearn/models/linear_regression.py
rootlearn/models/multi_linear_regression.py
rootlearn-0.2.1.dist-info/licenses/LICENSE
rootlearn-0.2.1.dist-info/METADATA
rootlearn-0.2.1.dist-info/WHEEL
rootlearn-0.2.1.dist-info/top_level.txt
rootlearn-0.2.1.dist-info/RECORD
